cqepyutils/__init__.py
cqepyutils/API/__init__.py
cqepyutils/CommonUtils/__init__.py
cqepyutils/CommonUtils/DBUtils/DBUtils.py
cqepyutils/CommonUtils/DBUtils/__init__.py
cqepyutils/CommonUtils/FileUtils/FileUtils.py
cqepyutils/CommonUtils/FileUtils/__init__.py
cqepyutils/CommonUtils/PandasUtils/PandasUtils.py
cqepyutils/CommonUtils/PandasUtils/__init__.py
cqepyutils/CommonUtils/RFUtils/DynamicTestCases.py
cqepyutils/CommonUtils/RFUtils/RFUtils.py
cqepyutils/CommonUtils/RFUtils/__init__.py
cqepyutils/CommonUtils/Reference/DBUtils_BK.py
cqepyutils/CommonUtils/Reference/PandasUtils_BK.py
cqepyutils/CommonUtils/Reference/__init__.py
cqepyutils/CommonUtils/Reference/DuckDBUtils/ChatBot.py
cqepyutils/CommonUtils/Reference/DuckDBUtils/ColmCompare.py
cqepyutils/CommonUtils/Reference/DuckDBUtils/CreateAnimeCharacter.py
cqepyutils/CommonUtils/Reference/DuckDBUtils/DuckDBUtils.py
cqepyutils/CommonUtils/Reference/DuckDBUtils/DuckDBUtils1.py
cqepyutils/CommonUtils/Reference/DuckDBUtils/LargefileCompareusingDask.py
cqepyutils/CommonUtils/Reference/DuckDBUtils/Largefilecompare.py
cqepyutils/CommonUtils/Reference/DuckDBUtils/PromptEngineering.py
cqepyutils/CommonUtils/Reference/DuckDBUtils/__init__.py
cqepyutils/CommonUtils/Reference/FileCompareUtils/HugeFileCompare.py
cqepyutils/CommonUtils/Reference/FileCompareUtils/__init__.py
cqepyutils/CommonUtils/Reference/JSONUtils/JSONUtils.py
cqepyutils/CommonUtils/Reference/JSONUtils/__init__.py
cqepyutils/CommonUtils/Reference/PlotlyUtils/RFPlotlyUtils.py
cqepyutils/CommonUtils/Reference/PlotlyUtils/__init__.py
cqepyutils/CommonUtils/Reference/RESTAPIUtils/RESTAPIUtils.py
cqepyutils/CommonUtils/Reference/RESTAPIUtils/__init__.py
cqepyutils/CommonUtils/Reference/TDMUtils/TestDataCreation.py
cqepyutils/CommonUtils/Reference/TDMUtils/__init__.py
cqepyutils/CommonUtils/Reference/ZephyrUtils/RFZephyrUtils.py
cqepyutils/CommonUtils/Reference/ZephyrUtils/__init__.py
cqepyutils/MFC/MFC.py
cqepyutils/MFC/__init__.py
cqepyutils-0.1.86.dist-info/LICENSE
cqepyutils-0.1.86.dist-info/METADATA
cqepyutils-0.1.86.dist-info/WHEEL
cqepyutils-0.1.86.dist-info/top_level.txt
cqepyutils-0.1.86.dist-info/RECORD
