Metadata-Version: 2.1
Name: cqepyutils
Version: 0.1.86
Summary: Cognitive Quality Engineer - Python Reusable Function Library
Home-page: https://github.com/cognitiveqe/cqepyutils/
Author: Sridhar VP
Author-email: sridharvpmca@gmail.com
License: MIT
Keywords: Python Reusable Function Library
Platform: any
Classifier: Programming Language :: Python :: 3
Classifier: License :: OSI Approved :: MIT License
Classifier: Operating System :: OS Independent
Classifier: Topic :: Software Development :: Testing
Classifier: Development Status :: 5 - Production/Stable
Requires-Python: >=3.6
License-File: LICENSE
Requires-Dist: pandas
Requires-Dist: numpy
Requires-Dist: matplotlib
Requires-Dist: xlsxwriter
Requires-Dist: openpyxl
Requires-Dist: sqlalchemy
Requires-Dist: oracledb
Requires-Dist: requests
Requires-Dist: robotframework
Requires-Dist: robotframework-requests
Requires-Dist: robotframework-seleniumlibrary
Requires-Dist: jinja2
Requires-Dist: pyyaml
Requires-Dist: lxml
Requires-Dist: ipython
Requires-Dist: jupyterlab
Requires-Dist: notebook
Requires-Dist: natsort
Requires-Dist: jupyterlab-robotmode
Requires-Dist: plotly
Requires-Dist: fsspec
Requires-Dist: twine
Requires-Dist: wheel
Requires-Dist: xmltodict
